shareyourcloning/__init__.py
shareyourcloning/assembly2.py
shareyourcloning/batch_cloning/__init__.py
shareyourcloning/batch_cloning/index.html
shareyourcloning/batch_cloning/pombe/__init__.py
shareyourcloning/batch_cloning/pombe/index.html
shareyourcloning/batch_cloning/pombe/pombe_all.sh
shareyourcloning/batch_cloning/pombe/pombe_clone.py
shareyourcloning/batch_cloning/pombe/pombe_gather.py
shareyourcloning/batch_cloning/pombe/pombe_get_primers.py
shareyourcloning/batch_cloning/pombe/pombe_summary.py
shareyourcloning/batch_cloning/ziqiang_et_al2024/__init__.py
shareyourcloning/batch_cloning/ziqiang_et_al2024/index.html
shareyourcloning/batch_cloning/ziqiang_et_al2024/ziqiang_et_al2024.json
shareyourcloning/dna_functions.py
shareyourcloning/dna_utils.py
shareyourcloning/endpoints/annotation.py
shareyourcloning/endpoints/assembly.py
shareyourcloning/endpoints/external_import.py
shareyourcloning/endpoints/no_assembly.py
shareyourcloning/endpoints/no_input.py
shareyourcloning/endpoints/other.py
shareyourcloning/endpoints/primer_design.py
shareyourcloning/gateway.py
shareyourcloning/get_router.py
shareyourcloning/main.py
shareyourcloning/ncbi_requests.py
shareyourcloning/primer_design.py
shareyourcloning/pydantic_models.py
shareyourcloning/record_stub_route.py
shareyourcloning/request_examples.py
shareyourcloning/utils.py
shareyourcloning-0.1.0.dist-info/LICENSE
shareyourcloning-0.1.0.dist-info/METADATA
shareyourcloning-0.1.0.dist-info/WHEEL
shareyourcloning-0.1.0.dist-info/RECORD
