Metadata-Version: 2.1
Name: shareyourcloning
Version: 0.1.0
Summary: Backend of ShareYourCloning, a web application to generate molecular cloning strategies in json format, and share them with others.
Home-page: https://github.com/manulera/shareyourcloning_backend
License: MIT
Author: Manuel Lera-Ramirez
Author-email: manulera14@gmail.com
Requires-Python: >=3.11,<4.0
Classifier: License :: OSI Approved :: MIT License
Classifier: Programming Language :: Python :: 3
Classifier: Programming Language :: Python :: 3.11
Classifier: Programming Language :: Python :: 3.12
Classifier: Programming Language :: Python :: 3.13
Requires-Dist: beautifulsoup4 (>=4.11.1,<5.0.0)
Requires-Dist: fastapi
Requires-Dist: httpx (>=0.25.0,<0.26.0)
Requires-Dist: openpyxl (>=3.1.5,<4.0.0)
Requires-Dist: pandas (>=2.2.3,<3.0.0)
Requires-Dist: pydantic (>=2.7.1,<3.0.0)
Requires-Dist: pydna (>=5.3,<6.0)
Requires-Dist: python-multipart
Requires-Dist: pyyaml (>=6.0.2,<7.0.0)
Requires-Dist: regex (>=2023.10.3,<2024.0.0)
Requires-Dist: requests (>=2.31.0,<3.0.0)
Requires-Dist: shareyourcloning-linkml (==0.1.11a0)
Requires-Dist: uvicorn
Project-URL: Repository, https://github.com/manulera/shareyourcloning_backend
